myrrh/core/exts/__init__.py
myrrh/core/exts/client.py
myrrh/core/exts/errors.py
myrrh/core/exts/interfaces.py
myrrh/core/exts/misc.py
myrrh/core/exts/protocol.py
myrrh/core/exts/registry.py
myrrh/extensions/mregistry.py
myrrh/tools/mexts.py
myrrh_core_exts-0.1.0.dist-info/AUTHORS.md
myrrh_core_exts-0.1.0.dist-info/LICENSE
myrrh_core_exts-0.1.0.dist-info/METADATA
myrrh_core_exts-0.1.0.dist-info/WHEEL
myrrh_core_exts-0.1.0.dist-info/entry_points.txt
myrrh_core_exts-0.1.0.dist-info/top_level.txt
myrrh_core_exts-0.1.0.dist-info/RECORD
